cfec/__init__.py
cfec/base.py
cfec/constraints/__init__.py
cfec/constraints/_freeze.py
cfec/constraints/_max_difference.py
cfec/constraints/_monotocity.py
cfec/constraints/_nominal.py
cfec/constraints/_one_hot.py
cfec/constraints/_utils.py
cfec/constraints/_value_change_direction.py
cfec/constraints/_value_range.py
cfec/explainers/__init__.py
cfec/explainers/_cadex.py
cfec/explainers/_cadex_parallel.py
cfec/explainers/_ece.py
cfec/explainers/_fimap.py
cfec/preprocessing/__init__.py
cfec/preprocessing/_data_frame_mapper.py
cfec/visualization/__init__.py
cfec/visualization/_visualization.py
CFEC-0.0.5.dist-info/LICENSE
CFEC-0.0.5.dist-info/METADATA
CFEC-0.0.5.dist-info/WHEEL
CFEC-0.0.5.dist-info/top_level.txt
CFEC-0.0.5.dist-info/RECORD
