Metadata-Version: 2.1
Name: CFEC
Version: 0.0.5
Summary: Python package for counterfactuals generation and presentation
Home-page: https://github.com/LoGosX/CFEC
Author: Zuzanna Trafas, Adam Wojciechowski, Maciej Falbogowski
Author-email: maciej.falbogowski@gmail.com
License: UNKNOWN
Project-URL: Bug Tracker, https://github.com/LoGosX/CFEC/issues
Platform: UNKNOWN
Classifier: Programming Language :: Python :: 3
Classifier: License :: OSI Approved :: MIT License
Classifier: Operating System :: OS Independent
Requires-Python: >=3.7
License-File: LICENSE
Requires-Dist: tensorflow (>=2.7.0)
Requires-Dist: pandas (>=1.3.5)
Requires-Dist: numpy (>=1.21.5)
Requires-Dist: scikit-learn (>=1.0.2)
Requires-Dist: psutil (>=5.8.0)
Requires-Dist: joblib (>=1.1.0)
Provides-Extra: testing
Requires-Dist: pytest (>=6.0) ; extra == 'testing'
Requires-Dist: pytest-cov (>=2.0) ; extra == 'testing'
Requires-Dist: mypy (>=0.910) ; extra == 'testing'
Requires-Dist: flake8 (>=3.9) ; extra == 'testing'
Requires-Dist: tox (>=3.24) ; extra == 'testing'
